baud_gen.v
module baud_gen #( parameter DVSR_WIDTH = 8; ) (clk,reset,dvsr,tick);

    // Wire and register definitions // 
    input wire clk; 
    input wire reset;
    input wire [DVSR_WIDTH-1:0] dvsr; // 10 bit divisior value
    output reg tick;    // output trigger

    reg [DVSR_WIDTH-1:0] r_reg;   // 10 bit register to keep counter

    // -- Control Counter -- //
    always @(posedge clk or posedge reset) begin
        if(reset) 
            r_reg <= 0;
        else if (r_reg == dvsr) //If counter reaches the dvst, reset counter
            r_reg <= 0;
        else
            r_reg <= r_reg + 1;
    end

    // -- Control Tick -- //
    always @(posedge clk or posedge reset) begin
        if(reset)
            tick <= 0;
        else if(r_reg == dvsr) // If counter reaches the DVSR, trigger tick 
            tick <= 1;
        else
            tick <= 0;
    end

endmodule

behaivoral_tests/baud_gen_tb/baud_gen_tb.sv
`timescale 1ns / 1ps

module baud_gen_tb;

    // Testbench Signals
    reg clk;
    reg reset;
    reg [8-1:0] dvsr;
    wire tick;

    // Instantiate the timer module
    baud_gen uut (
        .clk(clk),
        .reset(reset),
        .dvsr(dvsr),
        .tick(tick)
    );

    // Clock Generation (100 MHz clock -> period is 10 ns)
    always #5 clk = ~clk; // 5 ns high and 5 ns low

    // Testbench Logic
    initial begin
        // Initialize signals
        clk = 0;
        reset = 1;
        dvsr = 8'd54; // Adjusted for 9600 baud rate
        #10; // Wait for the reset

        reset = 0;
        
        // Run the simulation for a certain period to observe ticks
        #1000; // Run for 1000 ns (1 us)

        // End the simulation
        $finish;
    end

    // Detailed Monitoring to Observe Ticks
    initial begin
        $monitor("Time = %t ns, DVSR = %d, Tick = %b", $time, dvsr, tick);

        // Initialize VCD dump
        $dumpfile("behaivoral_tests/vcd/baud_gen_tb.vcd");
        $dumpvars(0, baud_gen_tb);

    end

endmodule

behaivoral_tests/vcd/baud_gen_tb.vcd
$date
	Wed Jan 17 16:27:53 2024
$end
$version
	Icarus Verilog
$end
$timescale
	1ps
$end
$scope module baud_gen_tb $end
$var wire 1 ! tick $end
$var reg 1 " clk $end
$var reg 8 # dvsr [7:0] $end
$var reg 1 $ reset $end
$scope module uut $end
$var wire 1 " clk $end
$var wire 8 % dvsr [7:0] $end
$var wire 1 $ reset $end
$var reg 8 & r_reg [7:0] $end
$var reg 1 ! tick $end
$upscope $end
$upscope $end
$enddefinitions $end
$comment Show the parameter values. $end
$dumpall
$end
#0
$dumpvars
b0 &
b110110 %
1$
b110110 #
0"
0!
$end
#5000
1"
#10000
0"
0$
#15000
b1 &
1"
#20000
0"
#25000
b10 &
1"
#30000
0"
#35000
b11 &
1"
#40000
0"
#45000
b100 &
1"
#50000
0"
#55000
b101 &
1"
#60000
0"
#65000
b110 &
1"
#70000
0"
#75000
b111 &
1"
#80000
0"
#85000
b1000 &
1"
#90000
0"
#95000
b1001 &
1"
#100000
0"
#105000
b1010 &
1"
#110000
0"
#115000
b1011 &
1"
#120000
0"
#125000
b1100 &
1"
#130000
0"
#135000
b1101 &
1"
#140000
0"
#145000
b1110 &
1"
#150000
0"
#155000
b1111 &
1"
#160000
0"
#165000
b10000 &
1"
#170000
0"
#175000
b10001 &
1"
#180000
0"
#185000
b10010 &
1"
#190000
0"
#195000
b10011 &
1"
#200000
0"
#205000
b10100 &
1"
#210000
0"
#215000
b10101 &
1"
#220000
0"
#225000
b10110 &
1"
#230000
0"
#235000
b10111 &
1"
#240000
0"
#245000
b11000 &
1"
#250000
0"
#255000
b11001 &
1"
#260000
0"
#265000
b11010 &
1"
#270000
0"
#275000
b11011 &
1"
#280000
0"
#285000
b11100 &
1"
#290000
0"
#295000
b11101 &
1"
#300000
0"
#305000
b11110 &
1"
#310000
0"
#315000
b11111 &
1"
#320000
0"
#325000
b100000 &
1"
#330000
0"
#335000
b100001 &
1"
#340000
0"
#345000
b100010 &
1"
#350000
0"
#355000
b100011 &
1"
#360000
0"
#365000
b100100 &
1"
#370000
0"
#375000
b100101 &
1"
#380000
0"
#385000
b100110 &
1"
#390000
0"
#395000
b100111 &
1"
#400000
0"
#405000
b101000 &
1"
#410000
0"
#415000
b101001 &
1"
#420000
0"
#425000
b101010 &
1"
#430000
0"
#435000
b101011 &
1"
#440000
0"
#445000
b101100 &
1"
#450000
0"
#455000
b101101 &
1"
#460000
0"
#465000
b101110 &
1"
#470000
0"
#475000
b101111 &
1"
#480000
0"
#485000
b110000 &
1"
#490000
0"
#495000
b110001 &
1"
#500000
0"
#505000
b110010 &
1"
#510000
0"
#515000
b110011 &
1"
#520000
0"
#525000
b110100 &
1"
#530000
0"
#535000
b110101 &
1"
#540000
0"
#545000
b110110 &
1"
#550000
0"
#555000
b0 &
1!
1"
#560000
0"
#565000
0!
b1 &
1"
#570000
0"
#575000
b10 &
1"
#580000
0"
#585000
b11 &
1"
#590000
0"
#595000
b100 &
1"
#600000
0"
#605000
b101 &
1"
#610000
0"
#615000
b110 &
1"
#620000
0"
#625000
b111 &
1"
#630000
0"
#635000
b1000 &
1"
#640000
0"
#645000
b1001 &
1"
#650000
0"
#655000
b1010 &
1"
#660000
0"
#665000
b1011 &
1"
#670000
0"
#675000
b1100 &
1"
#680000
0"
#685000
b1101 &
1"
#690000
0"
#695000
b1110 &
1"
#700000
0"
#705000
b1111 &
1"
#710000
0"
#715000
b10000 &
1"
#720000
0"
#725000
b10001 &
1"
#730000
0"
#735000
b10010 &
1"
#740000
0"
#745000
b10011 &
1"
#750000
0"
#755000
b10100 &
1"
#760000
0"
#765000
b10101 &
1"
#770000
0"
#775000
b10110 &
1"
#780000
0"
#785000
b10111 &
1"
#790000
0"
#795000
b11000 &
1"
#800000
0"
#805000
b11001 &
1"
#810000
0"
#815000
b11010 &
1"
#820000
0"
#825000
b11011 &
1"
#830000
0"
#835000
b11100 &
1"
#840000
0"
#845000
b11101 &
1"
#850000
0"
#855000
b11110 &
1"
#860000
0"
#865000
b11111 &
1"
#870000
0"
#875000
b100000 &
1"
#880000
0"
#885000
b100001 &
1"
#890000
0"
#895000
b100010 &
1"
#900000
0"
#905000
b100011 &
1"
#910000
0"
#915000
b100100 &
1"
#920000
0"
#925000
b100101 &
1"
#930000
0"
#935000
b100110 &
1"
#940000
0"
#945000
b100111 &
1"
#950000
0"
#955000
b101000 &
1"
#960000
0"
#965000
b101001 &
1"
#970000
0"
#975000
b101010 &
1"
#980000
0"
#985000
b101011 &
1"
#990000
0"
#995000
b101100 &
1"
#1000000
0"
#1005000
b101101 &
1"
